MaxHeap
