Metadata-Version: 2.1
Name: MaxHeap
Version: 1.3
Summary: A beta version of a max-Heap that utilizes numpy memmaps so memory consumption can be reduced.
Home-page: https://www.inventorsniche.com
Author: Harold J. Iwen
Author-email: inventorsniche349@gmail.com
License: MIT
Download-URL: https://github.com/Hiwen-STEM/MaxHeap
Keywords: Binary_Tree,Heap,Tree,Max_Heap,Binary
Platform: UNKNOWN
Classifier: Development Status :: 4 - Beta
Classifier: Intended Audience :: Developers
Classifier: Topic :: Software Development :: Build Tools
Classifier: License :: OSI Approved :: MIT License
Classifier: Programming Language :: Python :: 3.6
Classifier: Programming Language :: Python :: 3.7
Classifier: Programming Language :: Python :: 3.8
